rtm_doorstop.py
rtm_doorstop-1.1.1.dist-info/LICENSE
rtm_doorstop-1.1.1.dist-info/METADATA
rtm_doorstop-1.1.1.dist-info/WHEEL
rtm_doorstop-1.1.1.dist-info/entry_points.txt
rtm_doorstop-1.1.1.dist-info/top_level.txt
rtm_doorstop-1.1.1.dist-info/RECORD
