Metadata-Version: 2.1
Name: rtm-doorstop
Version: 1.1.1
Summary: A tool to generate Requirement Traceability Matrices (RTMs) from Doorstop documents.
Home-page: https://github.com/scuriosity/rtm_doorstop
Author: Andrew Simon
Author-email: asimon1@protonmail.com
Maintainer: Andrew Simon
Maintainer-email: asimon1@protonmail.com
License: GNU GPL v3.0
Platform: UNKNOWN
Classifier: Development Status :: 4 - Beta
Classifier: Environment :: Console
Classifier: Topic :: Software Development :: Quality Assurance
Classifier: Programming Language :: Python
Classifier: Programming Language :: Python :: 3
Classifier: Operating System :: OS Independent
Classifier: License :: OSI Approved :: GNU General Public License v3 (GPLv3)
Requires-Python: >=3.7
Requires-Dist: doorstop (>=2.0.0)
Requires-Dist: rapidtables (>=0.1)
Requires-Dist: fire (>=0.3)
